4bit_barrel_shifter.v
module barrel_shifter_4bit(
input [3:0]data_in,
input [1:0]shift_amt,
input [2:0]mode,
output reg [3:0]data_out
);

always@(*) begin
case(mode)
3'b000: data_out = (data_in << shift_amt); //Logical Left Shift
3'b001: data_out = (data_in >> shift_amt); //Logical Right Shift
3'b010: data_out = data_in <<< shift_amt; // Arithmetic Left (same as logical left in unsigned 4-bit)
3'b011: data_out = $signed(data_in) >>> shift_amt; // Arithmetic Right (sign-preserving)
3'b100: data_out = (data_in << shift_amt) | (data_in >> (4-shift_amt)); //Rotate Left shift
3'b101: data_out = (data_in >> shift_amt) | (data_in << (4-shift_amt)); //Rotate Right Shift
default: data_out = data_in;
endcase
end

endmodule

4bit_barrel_shifter_tb.v
module barrel_shifter_4bit_tb();
reg [3:0]data_in;
reg [1:0]shift_amt;
reg [2:0]mode;
wire [3:0]data_out;

barrel_shifter_4bit uut(.data_in(data_in), .shift_amt(shift_amt), .mode(mode), .data_out(data_out));

initial begin
data_in = 4'b0000;
shift_amt = 2'b00;
mode = 3'b000;

data_in = 4'b1011;
mode = 3'b000; shift_amt = 2'b01; #10
mode = 3'b001; shift_amt = 2'b10; #10
mode = 3'b010; shift_amt = 2'b10; #10
mode = 3'b011; shift_amt = 2'b10; #10
mode = 3'b100; shift_amt = 2'b11; #10
mode = 3'b101; shift_amt = 2'b10; #10

data_in = 4'b1001;
mode = 3'b000; shift_amt = 2'b01; #10
mode = 3'b001; shift_amt = 2'b10; #10
mode = 3'b010; shift_amt = 2'b10; #10
mode = 3'b011; shift_amt = 2'b10; #10
mode = 3'b100; shift_amt = 2'b11; #10
mode = 3'b101; shift_amt = 2'b10; #10

data_in = 4'b1101;
mode = 3'b000; shift_amt = 2'b01; #10
mode = 3'b001; shift_amt = 2'b10; #10
mode = 3'b010; shift_amt = 2'b10; #10
mode = 3'b011; shift_amt = 2'b10; #10
mode = 3'b100; shift_amt = 2'b11; #10
mode = 3'b101; shift_amt = 2'b10; #10

data_in = 4'b0110;
mode = 3'b000; shift_amt = 2'b01; #10
mode = 3'b001; shift_amt = 2'b10; #10
mode = 3'b010; shift_amt = 2'b10; #10
mode = 3'b011; shift_amt = 2'b10; #10
mode = 3'b100; shift_amt = 2'b11; #10
mode = 3'b101; shift_amt = 2'b10; #10
$finish;
end

endmodule

waveform.vcd
$date
   Fri Sep  5 12:53:58 2025
$end

$version
  2025.1.0
  $dumpfile ("waveform.vcd") 
$end

$timescale
  1ps
$end

$scope module barrel_shifter_4bit_tb $end
$var reg 4 ! data_in [3:0] $end
$var reg 2 " shift_amt [1:0] $end
$var reg 3 # mode [2:0] $end
$var wire 4 $ data_out [3:0] $end
$scope module uut $end
$var wire 4 % data_in [3:0] $end
$var wire 2 & shift_amt [1:0] $end
$var wire 3 ' mode [2:0] $end
$var reg 4 ( data_out [3:0] $end
$upscope $end
$upscope $end
$enddefinitions $end

#0
$dumpvars
b1011 !
b1 "
b0 #
b110 $
b1011 %
b1 &
b0 '
b110 (
$end

#10000
b10 "
b1 #
b10 $
b10 &
b1 '
b10 (

#20000
b10 #
b1100 $
b10 '
b1100 (

#30000
b11 #
b1110 $
b11 '
b1110 (

#40000
b11 "
b100 #
b1101 $
b11 &
b100 '
b1101 (

#50000
b10 "
b101 #
b1110 $
b10 &
b101 '
b1110 (

#60000
b1001 !
b1 "
b0 #
b10 $
b1001 %
b1 &
b0 '
b10 (

#70000
b10 "
b1 #
b10 &
b1 '

#80000
b10 #
b100 $
b10 '
b100 (

#90000
b11 #
b1110 $
b11 '
b1110 (

#100000
b11 "
b100 #
b1100 $
b11 &
b100 '
b1100 (

#110000
b10 "
b101 #
b110 $
b10 &
b101 '
b110 (

#120000
b1101 !
b1 "
b0 #
b1010 $
b1101 %
b1 &
b0 '
b1010 (

#130000
b10 "
b1 #
b11 $
b10 &
b1 '
b11 (

#140000
b10 #
b100 $
b10 '
b100 (

#150000
b11 #
b1111 $
b11 '
b1111 (

#160000
b11 "
b100 #
b1110 $
b11 &
b100 '
b1110 (

#170000
b10 "
b101 #
b111 $
b10 &
b101 '
b111 (

#180000
b110 !
b1 "
b0 #
b1100 $
b110 %
b1 &
b0 '
b1100 (

#190000
b10 "
b1 #
b1 $
b10 &
b1 '
b1 (

#200000
b10 #
b1000 $
b10 '
b1000 (

#210000
b11 #
b1 $
b11 '
b1 (

#220000
b11 "
b100 #
b11 $
b11 &
b100 '
b11 (
